{"dataURL":"file:\/\/\/Users\/rafaelferreirarodrigues\/Downloads\/Notas\/","id":"DD3AFDAB-DF10-4807-A3A2-2A69F09D03B3","createdDate":"2020-11-13T19:31:24Z","title":"Notas","modifiedDate":"2020-11-13T19:37:47Z","preferredFilename":"Notas","version":"1.0","dataResult":{"itemsCount":842,"dataURL":"file:\/\/\/Users\/rafaelferreirarodrigues\/Downloads\/Notas\/","classesCount":7,"analysis":{"summary":{"canUseValidation":1,"classCount":7,"sampleCount":842},"issues":[{"description":"7 classes found, including 20 nova, 10 reais nova, 50 nova","severity":"debug"},{"description":"842 images found, automatically creating validation set","severity":"good"},{"description":"Smallest class is \"100 antiga\" with 83 images","severity":"debug"},{"description":"Largest class is \"20 nova\" with 171 images","severity":"debug"}],"classifierAnalysis":{"columns":[],"vizualizerSpec":"","labelStats":{"100 antiga":83,"20 nova":171,"2 Reais":99,"10 reais nova":146,"200 ":99,"100 nova":110,"50 nova":134}}}},"activityEntities":["dataSourceTrainingStarted",[{"id":"1CBDEA65-DEAA-404E-ABFB-ED7C863F81E8","title":"Used By","createdDate":"2020-11-13T19:32:05Z","event":"dataSourceTrainingStarted","subtitle":"BillClassifier 1"}],"dataSourceMetrics",[{"id":"719CC6DB-BD4E-4C39-9C19-E292527B0AA7","title":"Data Summary","createdDate":"2020-11-13T19:32:05Z","event":"dataSourceMetrics","subtitle":"7 Classes, 842 Items"}],"dataSourceCreated",[{"id":"C362E1B5-F3F8-48AD-ADBB-7DC505AF8A5D","title":"Data Source Created","createdDate":"2020-11-13T19:31:24Z","event":"dataSourceCreated","subtitle":"Notas"}]],"pathType":0,"experimentIDs":["EA1B2CE5-9EBB-4D86-A62F-AA0D3406D937"]}